buildbot_scheduler_graph.py
setup.py
buildbot_scheduler_graph.egg-info/PKG-INFO
buildbot_scheduler_graph.egg-info/SOURCES.txt
buildbot_scheduler_graph.egg-info/dependency_links.txt
buildbot_scheduler_graph.egg-info/entry_points.txt
buildbot_scheduler_graph.egg-info/not-zip-safe
buildbot_scheduler_graph.egg-info/requires.txt
buildbot_scheduler_graph.egg-info/top_level.txt