Metadata-Version: 1.0
Name: buildbot-scheduler-graph
Version: 1.0
Summary: A tool for generating digraphs of Buildbot Builders and Schedulers
Home-page: UNKNOWN
Author: Ben Hearsum
Author-email: UNKNOWN
License: UNKNOWN
Platform: UNKNOWN
